<annotation>
	<folder>own_database</folder>
	<filename>coco_2.jpg</filename>
	<path>C:\Users\Kubin\Desktop\ASO_CV\own_database\coco_2.jpg</path>
	<source>
		<database>Unknown</database>
	</source>
	<size>
		<width>3024</width>
		<height>4032</height>
		<depth>3</depth>
	</size>
	<segmented>0</segmented>
	<object>
		<name>cocolino</name>
		<pose>Unspecified</pose>
		<truncated>0</truncated>
		<difficult>0</difficult>
		<bndbox>
			<xmin>1194</xmin>
			<ymin>1191</ymin>
			<xmax>2409</xmax>
			<ymax>3026</ymax>
		</bndbox>
	</object>
</annotation>
