<annotation>
	<folder>rotated</folder>
	<filename>IMG_7554.jpg</filename>
	<path>C:\Users\Patrycja\Downloads\Aso\images\rotated\IMG_7554.jpg</path>
	<source>
		<database>Unknown</database>
	</source>
	<size>
		<width>4284</width>
		<height>5712</height>
		<depth>3</depth>
	</size>
	<segmented>0</segmented>
	<object>
		<name>Milk</name>
		<pose>Unspecified</pose>
		<truncated>0</truncated>
		<difficult>0</difficult>
		<bndbox>
			<xmin>2738</xmin>
			<ymin>1402</ymin>
			<xmax>3513</xmax>
			<ymax>2902</ymax>
		</bndbox>
	</object>
	<object>
		<name>Milk</name>
		<pose>Unspecified</pose>
		<truncated>0</truncated>
		<difficult>0</difficult>
		<bndbox>
			<xmin>2182</xmin>
			<ymin>1340</ymin>
			<xmax>2744</xmax>
			<ymax>2790</ymax>
		</bndbox>
	</object>
	<object>
		<name>Milk</name>
		<pose>Unspecified</pose>
		<truncated>0</truncated>
		<difficult>0</difficult>
		<bndbox>
			<xmin>1519</xmin>
			<ymin>1446</ymin>
			<xmax>2307</xmax>
			<ymax>2815</ymax>
		</bndbox>
	</object>
	<object>
		<name>Milk</name>
		<pose>Unspecified</pose>
		<truncated>0</truncated>
		<difficult>0</difficult>
		<bndbox>
			<xmin>794</xmin>
			<ymin>1409</ymin>
			<xmax>1732</xmax>
			<ymax>2840</ymax>
		</bndbox>
	</object>
	<object>
		<name>Milk</name>
		<pose>Unspecified</pose>
		<truncated>1</truncated>
		<difficult>0</difficult>
		<bndbox>
			<xmin>851</xmin>
			<ymin>4540</ymin>
			<xmax>1852</xmax>
			<ymax>5712</ymax>
		</bndbox>
	</object>
</annotation>
