<annotation>
	<folder>rotated</folder>
	<filename>IMG_7611.jpg</filename>
	<path>C:\Users\Patrycja\Downloads\Aso\images\rotated\IMG_7611.jpg</path>
	<source>
		<database>Unknown</database>
	</source>
	<size>
		<width>4284</width>
		<height>5712</height>
		<depth>3</depth>
	</size>
	<segmented>0</segmented>
	<object>
		<name>Coca Cola</name>
		<pose>Unspecified</pose>
		<truncated>0</truncated>
		<difficult>0</difficult>
		<bndbox>
			<xmin>2307</xmin>
			<ymin>1046</ymin>
			<xmax>3501</xmax>
			<ymax>4796</ymax>
		</bndbox>
	</object>
	<object>
		<name>Coca Cola</name>
		<pose>Unspecified</pose>
		<truncated>0</truncated>
		<difficult>0</difficult>
		<bndbox>
			<xmin>1313</xmin>
			<ymin>1009</ymin>
			<xmax>2444</xmax>
			<ymax>4715</ymax>
		</bndbox>
	</object>
	<object>
		<name>Coca Cola</name>
		<pose>Unspecified</pose>
		<truncated>0</truncated>
		<difficult>0</difficult>
		<bndbox>
			<xmin>832</xmin>
			<ymin>1396</ymin>
			<xmax>1582</xmax>
			<ymax>3627</ymax>
		</bndbox>
	</object>
	<object>
		<name>Coca Cola</name>
		<pose>Unspecified</pose>
		<truncated>0</truncated>
		<difficult>0</difficult>
		<bndbox>
			<xmin>144</xmin>
			<ymin>1415</ymin>
			<xmax>994</xmax>
			<ymax>3771</ymax>
		</bndbox>
	</object>
</annotation>
