<annotation>
	<folder>rotated</folder>
	<filename>IMG_7560.jpg</filename>
	<path>C:\Users\Patrycja\Downloads\Aso\images\rotated\IMG_7560.jpg</path>
	<source>
		<database>Unknown</database>
	</source>
	<size>
		<width>4284</width>
		<height>5712</height>
		<depth>3</depth>
	</size>
	<segmented>0</segmented>
	<object>
		<name>Milk</name>
		<pose>Unspecified</pose>
		<truncated>0</truncated>
		<difficult>0</difficult>
		<bndbox>
			<xmin>2157</xmin>
			<ymin>959</ymin>
			<xmax>3701</xmax>
			<ymax>2696</ymax>
		</bndbox>
	</object>
	<object>
		<name>Milk</name>
		<pose>Unspecified</pose>
		<truncated>0</truncated>
		<difficult>0</difficult>
		<bndbox>
			<xmin>363</xmin>
			<ymin>909</ymin>
			<xmax>2176</xmax>
			<ymax>2727</ymax>
		</bndbox>
	</object>
	<object>
		<name>Milk</name>
		<pose>Unspecified</pose>
		<truncated>0</truncated>
		<difficult>0</difficult>
		<bndbox>
			<xmin>2076</xmin>
			<ymin>3134</ymin>
			<xmax>3388</xmax>
			<ymax>4471</ymax>
		</bndbox>
	</object>
	<object>
		<name>Milk</name>
		<pose>Unspecified</pose>
		<truncated>0</truncated>
		<difficult>0</difficult>
		<bndbox>
			<xmin>644</xmin>
			<ymin>2990</ymin>
			<xmax>2088</xmax>
			<ymax>4309</ymax>
		</bndbox>
	</object>
</annotation>
